scholtrack/__init__.py
scholtrack/api.py
scholtrack/cli.py
scholtrack/exporter.py
scholtrack/collections/4dgs.txt
scholtrack/collections/nvs.txt
scholtrack-0.1.0.1.dist-info/LICENSE
scholtrack-0.1.0.1.dist-info/METADATA
scholtrack-0.1.0.1.dist-info/WHEEL
scholtrack-0.1.0.1.dist-info/entry_points.txt
scholtrack-0.1.0.1.dist-info/top_level.txt
scholtrack-0.1.0.1.dist-info/RECORD
